mfglab/__init__.py
mfglab/com/__init__.py
mfglab/com/auto_detect.py
mfglab/com/rw.py
mfglab/config/__init__.py
mfglab/config/config.py
mfglab/config/log.py
mfglab/dshm/__init__.py
mfglab/dshm/dshm.py
mfglab/llm/__init__.py
mfglab/llm/inference.py
mfglab/llm/train.py
mfglab/rdbms/__init__.py
mfglab/rdbms/read.py
mfglab/rdbms/write.py
mfglab/tabular/__init__.py
mfglab/tabular/process.py
mfglab/tabular/rw.py
mfglab/utils/__init__.py
mfglab/utils/download.py
mfglab/vision/__init__.py
mfglab/vision/process.py
mfglab/vision/rw.py
mfglab/vision/anormaly/inference.py
mfglab/vision/anormaly/train.py
mfglab/vision/cls/inference.py
mfglab/vision/cls/train.py
mfglab/vision/od/inference.py
mfglab/vision/od/train.py
mfglab-0.1.0.dist-info/LICENSE
mfglab-0.1.0.dist-info/METADATA
mfglab-0.1.0.dist-info/WHEEL
mfglab-0.1.0.dist-info/top_level.txt
mfglab-0.1.0.dist-info/RECORD
